wild_time_data/__init__.py
wild_time_data/core.py
wild_time_data/datasets.py
wild_time_data/utils.py
wild_time_data-0.1.1.dist-info/LICENSE
wild_time_data-0.1.1.dist-info/METADATA
wild_time_data-0.1.1.dist-info/WHEEL
wild_time_data-0.1.1.dist-info/top_level.txt
wild_time_data-0.1.1.dist-info/RECORD
