Metadata-Version: 2.1
Name: wild-time-data
Version: 0.1.1
Summary: WILDS distribution shift data
Classifier: Development Status :: 3 - Alpha
Classifier: Intended Audience :: Developers
Classifier: Intended Audience :: Science/Research
Classifier: Topic :: Scientific/Engineering :: Artificial Intelligence
Classifier: License :: OSI Approved :: Apache Software License
Classifier: Programming Language :: Python :: 3
Requires-Python: >=3.8
License-File: LICENSE
Requires-Dist: gdown
Requires-Dist: h5py
Requires-Dist: torch
Requires-Dist: torchvision
